src/__init__.py
src/main.py
src/pin/__init__.py
src/pin/gpio.py
src/service/__init__.py
src/service/lightMotor.py
src/service/systemInfo.py
src/storage/__init__.py
src/storage/pinConfiguration.py
src/util/__init__.py
src/util/constants.py
src/util/errors.py
weedeia_greenbox_core-0.0.33.dist-info/METADATA
weedeia_greenbox_core-0.0.33.dist-info/WHEEL
weedeia_greenbox_core-0.0.33.dist-info/entry_points.txt
weedeia_greenbox_core-0.0.33.dist-info/top_level.txt
weedeia_greenbox_core-0.0.33.dist-info/RECORD
