Metadata-Version: 2.1
Name: weedeia-greenbox-core
Version: 0.0.33
Summary: API for GPIO admnistration
Author: Paulo Porto
Author-email: cesarpaulomp@gmail.com
Classifier: Development Status :: 1 - Planning
Classifier: Programming Language :: Python :: 3
Classifier: License :: OSI Approved :: MIT License
Classifier: Operating System :: OS Independent
Requires-Python: >=3.6
Requires-Dist: wheel
Requires-Dist: fastapi
Requires-Dist: uvicorn
Requires-Dist: tinydb
Requires-Dist: rpi.gpio
Requires-Dist: adafruit-circuitpython-dht
